<?xml version="1.0" encoding="UTF-8"?>
<con:testCase id="d9a1b71e-1259-46c5-84ed-73afc41f477b" discardOkResults="false" failOnError="true" failTestCaseOnErrors="true" keepSession="false" name="TestRuns_LoadByCriteria TestCase" searchProperties="true" timeout="0" maxResults="0" xmlns:con="http://eviware.com/soapui/config">
  <con:settings>
    <con:setting id="d9a1b71e-1259-46c5-84ed-73afc41f477bfileName">TestRuns_LoadByCriteria-TestCase</con:setting>
  </con:settings>
  <con:testStep type="request" id="bb222f1c-b52b-4c6f-af83-d29b78f0b006" name="TestRuns_LoadByCriteria">
    <con:settings/>
    <con:config xsi:type="con:RequestStep" xmlns:xsi="http://www.w3.org/2001/XMLSchema-instance">
      <con:interface>ServiceSoap</con:interface>
      <con:operation>TestRuns_LoadByCriteria</con:operation>
      <con:request name="TestRuns_LoadByCriteria" id="2104dd44-82ae-47d2-a7c9-2e8d0dcfdcf3">
        <con:settings/>
        <con:encoding>UTF-8</con:encoding>
        <con:endpoint>http://soap.qacomplete.smartbear.com/psWS.asmx</con:endpoint>
        <con:request><![CDATA[<soapenv:Envelope xmlns:soapenv="http://schemas.xmlsoap.org/soap/envelope/" xmlns:prag="http://www.pragmaticsw.com/">\r
   <soapenv:Header/>\r
   <soapenv:Body>\r
      <prag:TestRuns_LoadByCriteria>\r
         <!--Optional:-->\r
         <prag:AuthenticationData>\r
            <!--Optional:-->\r
            <prag:AppCode>?</prag:AppCode>\r
            <prag:DeptId>?</prag:DeptId>\r
            <prag:ProjId>?</prag:ProjId>\r
            <prag:UserId>?</prag:UserId>\r
            <!--Optional:-->\r
            <prag:PassCode>?</prag:PassCode>\r
            <!--Optional:-->\r
            <prag:ProjIds>\r
               <!--Zero or more repetitions:-->\r
               <prag:int>?</prag:int>\r
            </prag:ProjIds>\r
         </prag:AuthenticationData>\r
         <!--Optional:-->\r
         <prag:Condition>?</prag:Condition>\r
         <!--Optional:-->\r
         <prag:Sorting>?</prag:Sorting>\r
         <prag:PageSize>?</prag:PageSize>\r
         <prag:PageNumber>?</prag:PageNumber>\r
      </prag:TestRuns_LoadByCriteria>\r
   </soapenv:Body>\r
</soapenv:Envelope>]]></con:request>
        <con:credentials>
          <con:selectedAuthProfile>Inherit From Parent</con:selectedAuthProfile>
          <con:authType>No Authorization</con:authType>
        </con:credentials>
        <con:wsaConfig action="http://www.pragmaticsw.com/TestRuns_LoadByCriteria"/>
      </con:request>
    </con:config>
  </con:testStep>
  <con:properties/>
  <con:reportParameters/>
</con:testCase>
